htrest/__init__.py
htrest/__main__.py
htrest/__version__.py
htrest/apiv1.py
htrest/app.py
htrest/logging.conf
htrest/settings.py
htrest/apis/__init__.py
htrest/apis/date_time.py
htrest/apis/device.py
htrest/apis/fast_query.py
htrest/apis/fault_list.py
htrest/apis/param.py
htrest/apis/time_prog.py
htrest/apis/utils.py
htrest-0.1.11.dist-info/LICENSE
htrest-0.1.11.dist-info/METADATA
htrest-0.1.11.dist-info/WHEEL
htrest-0.1.11.dist-info/entry_points.txt
htrest-0.1.11.dist-info/top_level.txt
htrest-0.1.11.dist-info/RECORD
