Metadata-Version: 2.1
Name: htrest
Version: 0.1.11
Summary: Heliotherm heat pump REST API
Home-page: https://github.com/dstrigl/HtREST
Author: Daniel Strigl
License: GNU General Public License v3
Keywords: python python3 heatpump Heliotherm rest restful api flask swagger
Platform: Linux
Classifier: Development Status :: 4 - Beta
Classifier: Intended Audience :: Developers
Classifier: Intended Audience :: Information Technology
Classifier: Intended Audience :: Science/Research
Classifier: Intended Audience :: Manufacturing
Classifier: License :: OSI Approved :: GNU General Public License v3 (GPLv3)
Classifier: Programming Language :: Python
Classifier: Programming Language :: Python :: 3
Classifier: Programming Language :: Python :: 3.7
Classifier: Programming Language :: Python :: 3.8
Classifier: Natural Language :: English
Classifier: Operating System :: POSIX
Classifier: Operating System :: POSIX :: Linux
Classifier: Topic :: Communications
Classifier: Topic :: Home Automation
Classifier: Topic :: Internet :: WWW/HTTP
Classifier: Topic :: Internet :: WWW/HTTP :: HTTP Servers
Classifier: Topic :: Internet :: WWW/HTTP :: Dynamic Content
Classifier: Topic :: Scientific/Engineering
Classifier: Topic :: Terminals :: Serial
Requires-Dist: htheatpump (==1.3.2)
Requires-Dist: Flask (==2.0.3)
Requires-Dist: flask-restx (==0.5.1)
Requires-Dist: Flask-BasicAuth (==0.2.0)
Provides-Extra: dev
Requires-Dist: mypy (==0.931) ; extra == 'dev'
Requires-Dist: coverage (==6.3.2) ; extra == 'dev'
Requires-Dist: pytest (==7.0.1) ; extra == 'dev'
Requires-Dist: pytest-mypy (==0.9.1) ; extra == 'dev'
Requires-Dist: pytest-cov (==3.0.0) ; extra == 'dev'
Requires-Dist: pytest-sugar (==0.9.4) ; extra == 'dev'
Requires-Dist: flake8 (==4.0.1) ; extra == 'dev'
Requires-Dist: tox (==3.24.5) ; extra == 'dev'
Provides-Extra: doc
Provides-Extra: test
Requires-Dist: mypy (==0.931) ; extra == 'test'
Requires-Dist: coverage (==6.3.2) ; extra == 'test'
Requires-Dist: pytest (==7.0.1) ; extra == 'test'
Requires-Dist: pytest-mypy (==0.9.1) ; extra == 'test'
Requires-Dist: pytest-cov (==3.0.0) ; extra == 'test'
Requires-Dist: pytest-sugar (==0.9.4) ; extra == 'test'
